{"epochs": 30, "batch_size": 12, "learning_rate": 0.005, "max_seq_length": 1024, "checkpoint": 5, "device": "cuda:1", "optimizer": "SGD", "patience": 5, "train_epochs": 29, "local_model_path": "/mnt/pvc-data.common/ChenZikang/huggingface/", "model": {"text_model": "nomic-ai/nomic-embed-text-v1.5", "text_tokenizer": "nomic-ai/nomic-embed-text-v1.5"}, "schedualer": {"milestones": [20], "gamma": 0.5}, "weight_decay": 0, "start_epoch": 0, "start_epoch_timestamp": "", "load_model_dict_path": "", "save_model_dict_path": "/mnt/pvc-data.common/ChenZikang/codes/mm-BRAG/model_dict/text_ret/book/", "dataset_path": "/mnt/pvc-data.common/ChenZikang/codes/mm-BRAG/dataset/book_qa/book_qa_4o_rl.json", "comment": []}